cerealtest/__init__.py
cerealtest/cerealtest.py
cerealtest-0.2.0.dist-info/LICENSE.txt
cerealtest-0.2.0.dist-info/METADATA
cerealtest-0.2.0.dist-info/WHEEL
cerealtest-0.2.0.dist-info/top_level.txt
cerealtest-0.2.0.dist-info/RECORD
