Metadata-Version: 2.1
Name: cerealtest
Version: 0.2.0
Summary: Serial Port Test Automation
Home-page: https://github.com/guigarma/cerealtest
Author: Guillermo Eduardo Garcia Maynez
Author-email: garciamaynezg@gmail.com
License: UNKNOWN
Project-URL: Bug Tracker, https://github.com/guigarma/cerealtest/issues
Platform: UNKNOWN
Classifier: Programming Language :: Python :: 3
Classifier: License :: OSI Approved :: Mozilla Public License 2.0 (MPL 2.0)
Classifier: Operating System :: OS Independent
Requires-Python: >=3.8
License-File: LICENSE.txt
